gamerl/ppo/jax/__init__.py
gamerl/ppo/jax/ppo.py
gamerl/ppo/jax/ppo_examples.py
gamerl.ppo.jax-0.1.1.dist-info/LICENSE
gamerl.ppo.jax-0.1.1.dist-info/METADATA
gamerl.ppo.jax-0.1.1.dist-info/WHEEL
gamerl.ppo.jax-0.1.1.dist-info/top_level.txt
gamerl.ppo.jax-0.1.1.dist-info/RECORD
