Metadata-Version: 2.1
Name: gamerl.ppo.jax
Version: 0.1.1
Summary: JAX implementation of Proximal Policy Optimization
Author-email: pi-tau <pi.tau@yahoo.com>
License: MIT
Project-URL: Source, https://github.com/game-rl/ppo
Classifier: Programming Language :: Python :: 3
Classifier: License :: OSI Approved :: MIT License
Classifier: Operating System :: OS Independent
Requires-Python: >=3.7
License-File: LICENSE
Requires-Dist: jax
Requires-Dist: numpy
Requires-Dist: tqdm
